{
"lives": [
        {
                "name": "江苏移动",
                "type": 0,
                "url": "https://fastly.jsdelivr.net/gh/Kimentanm/aptv@master/m3u/jsyd.m3u",
                "epg": "http://epg.51zmt.top:8000/api/diyp/?ch={name}&date={date}",
                "logo": "https://epg.iill.top/logo/{name}.png",
                "ua": "okhttp/3.15",
        },
        {
                "name": "中国移动",
                "type": 0,
                "url": "https://fastly.jsdelivr.net/gh/wsl201/biu@main/zgyd.m3u",
                "epg": "http://epg.51zmt.top:8000/api/diyp/?ch={name}&date={date}",
                "logo": "https://epg.iill.top/logo/{name}.png",
                "ua": "okhttp/3.15"
        }
]
}
